choicefield/__init__.py
choicefield/_version.py
choicefield/fields.py
choicefield/py.typed
django_choicefield-0.2.3.dist-info/METADATA
django_choicefield-0.2.3.dist-info/WHEEL
django_choicefield-0.2.3.dist-info/licenses/LICENSE
django_choicefield-0.2.3.dist-info/RECORD
