Metadata-Version: 2.1
Name: django-choicefield
Version: 0.2.3
Summary: ChoiceField for Django models
Project-URL: Homepage, https://github.com/flaeppe/django-choicefield
Project-URL: Source, https://github.com/flaeppe/django-choicefield
Project-URL: Tracker, https://github.com/flaeppe/django-choicefield/issues
Author-email: Petter Friberg <petter_friberg@hotmail.com>
License-Expression: BSD-3-Clause
License-File: LICENSE
Keywords: choicefield,choices,django,field
Classifier: Development Status :: 4 - Beta
Classifier: Framework :: Django
Classifier: Framework :: Django :: 3.2
Classifier: Framework :: Django :: 4.0
Classifier: Framework :: Django :: 4.1
Classifier: Framework :: Django :: 4.2
Classifier: Framework :: Django :: 5.0
Classifier: Intended Audience :: Developers
Classifier: Operating System :: OS Independent
Classifier: Programming Language :: Python
Classifier: Programming Language :: Python :: 3 :: Only
Classifier: Programming Language :: Python :: 3.9
Classifier: Programming Language :: Python :: 3.10
Classifier: Programming Language :: Python :: 3.11
Classifier: Programming Language :: Python :: 3.12
Classifier: Typing :: Typed
Requires-Python: >=3.9
Requires-Dist: django>=3.2
Provides-Extra: test
Requires-Dist: django-stubs; extra == 'test'
Requires-Dist: parameterized; extra == 'test'
Requires-Dist: pytest; extra == 'test'
Requires-Dist: pytest-cov; extra == 'test'
Requires-Dist: pytest-django; extra == 'test'
